statgcb/__init__.py
statgcb-0.1.3.dist-info/METADATA
statgcb-0.1.3.dist-info/RECORD
statgcb-0.1.3.dist-info/WHEEL
statgcb-0.1.3.dist-info/top_level.txt
